{
    "frames": {
        "__bigButton.png": {
            "frame": {
                "x": 178,
                "y": 486,
                "w": 95,
                "h": 94
            }
        },
        "__buttonBackground.png": {
            "frame": {
                "x": 162,
                "y": 414,
                "w": 64,
                "h": 64
            }
        },
        "__cardBack.png": {
            "frame": {
                "x": 0,
                "y": 486,
                "w": 87,
                "h": 122
            }
        },
        "__cardFrame.png": {
            "frame": {
                "x": 89,
                "y": 486,
                "w": 87,
                "h": 122
            }
        },
        "__chatBackground.png": {
            "frame": {
                "x": 351,
                "y": 486,
                "w": 74,
                "h": 76
            }
        },
        "__checkboxBackground.png": {
            "frame": {
                "x": 427,
                "y": 523,
                "w": 18,
                "h": 18
            }
        },
        "__checkboxTick.png": {
            "frame": {
                "x": 594,
                "y": 486,
                "w": 21,
                "h": 16
            }
        },
        "__chip0.png": {
            "frame": {
                "x": 434,
                "y": 414,
                "w": 40,
                "h": 30
            }
        },
        "__chip1.png": {
            "frame": {
                "x": 602,
                "y": 414,
                "w": 40,
                "h": 30
            }
        },
        "__chip2.png": {
            "frame": {
                "x": 476,
                "y": 414,
                "w": 40,
                "h": 30
            }
        },
        "__chip3.png": {
            "frame": {
                "x": 518,
                "y": 414,
                "w": 40,
                "h": 30
            }
        },
        "__chip4.png": {
            "frame": {
                "x": 560,
                "y": 414,
                "w": 40,
                "h": 30
            }
        },
        "__dealerButton.png": {
            "frame": {
                "x": 427,
                "y": 486,
                "w": 41,
                "h": 35
            }
        },
        "__dialogButton.png": {
            "frame": {
                "x": 228,
                "y": 414,
                "w": 82,
                "h": 47
            }
        },
        "__dividerLine.png": {
            "frame": {
                "x": 774,
                "y": 0,
                "w": 2,
                "h": 170
            }
        },
        "__eleminatedTableIcon.png": {
            "frame": {
                "x": 228,
                "y": 463,
                "w": 13,
                "h": 13
            }
        },
        "__framePlate.png": {
            "frame": {
                "x": 275,
                "y": 486,
                "w": 74,
                "h": 76
            }
        },
        "__seatPlate.png": {
            "frame": {
                "x": 0,
                "y": 414,
                "w": 160,
                "h": 70
            }
        },
        "__selectTableButton.png": {
            "frame": {
                "x": 685,
                "y": 414,
                "w": 39,
                "h": 22
            }
        },
        "__selectedTableButton.png": {
            "frame": {
                "x": 644,
                "y": 414,
                "w": 39,
                "h": 22
            }
        },
        "__sliderBackground.png": {
            "frame": {
                "x": 312,
                "y": 414,
                "w": 120,
                "h": 30
            }
        },
        "__sliderKnob.png": {
            "frame": {
                "x": 504,
                "y": 486,
                "w": 28,
                "h": 28
            }
        },
        "__suitSymbol0.png": {
            "frame": {
                "x": 554,
                "y": 486,
                "w": 18,
                "h": 19
            }
        },
        "__suitSymbol1.png": {
            "frame": {
                "x": 574,
                "y": 486,
                "w": 18,
                "h": 19
            }
        },
        "__suitSymbol2.png": {
            "frame": {
                "x": 749,
                "y": 414,
                "w": 18,
                "h": 19
            }
        },
        "__suitSymbol3.png": {
            "frame": {
                "x": 534,
                "y": 486,
                "w": 18,
                "h": 19
            }
        },
        "__table.png": {
            "frame": {
                "x": 0,
                "y": 0,
                "w": 772,
                "h": 412
            }
        },
        "__textScrollbarThumb.png": {
            "frame": {
                "x": 374,
                "y": 446,
                "w": 60,
                "h": 10
            }
        },
        "__textScrollbarTrack.png": {
            "frame": {
                "x": 312,
                "y": 446,
                "w": 60,
                "h": 10
            }
        },
        "__timerBackground.png": {
            "frame": {
                "x": 470,
                "y": 486,
                "w": 32,
                "h": 32
            }
        },
        "__upArrow.png": {
            "frame": {
                "x": 436,
                "y": 446,
                "w": 12,
                "h": 8
            }
        },
        "__wrenchIcon.png": {
            "frame": {
                "x": 726,
                "y": 414,
                "w": 21,
                "h": 21
            }
        }
    },
    "meta": {
        "app": "spritesheet-templates",
        "version": "9.6.1",
        "image": "netpokerclient.spritesheet.png",
        "scale": 1,
        "size": {
            "w": 776,
            "h": 608
        }
    }
}